README.md
setup.py
obp_pad_composer.egg-info/PKG-INFO
obp_pad_composer.egg-info/SOURCES.txt
obp_pad_composer.egg-info/dependency_links.txt
obp_pad_composer.egg-info/entry_points.txt
obp_pad_composer.egg-info/requires.txt
obp_pad_composer.egg-info/top_level.txt
pad_composer/__init__.py
pad_composer/composer.py