Metadata-Version: 1.0
Name: obp-pad-composer
Version: 0.0.1
Summary: DAB+ Pad data composer (for Open Broadcast API)
Home-page: https://github.com/ohrstrom/obp-pad-composer
Author: Jonas Ohrstrom
Author-email: ohrstrom@gmail.com
License: UNKNOWN
Platform: UNKNOWN
